dockubeadt/__init__.py
dockubeadt/__main__.py
dockubeadt/cli.py
dockubeadt/compose.py
dockubeadt/kube.py
dockubeadt/translator.py
dockubeadt/utils.py
dockubeadt-0.3.4.dist-info/LICENSE
dockubeadt-0.3.4.dist-info/METADATA
dockubeadt-0.3.4.dist-info/WHEEL
dockubeadt-0.3.4.dist-info/entry_points.txt
dockubeadt-0.3.4.dist-info/top_level.txt
dockubeadt-0.3.4.dist-info/RECORD
