Metadata-Version: 2.1
Name: dockubeadt
Version: 0.3.4
Summary: Translate Docker compose and k8s manifests to a MiCADO ADT
Home-page: https://github.com/UoW-CPC/DocKubeADT
Author: Resmi Arjun / Jay DesLauriers
License: Apache 2.0
Project-URL: Bug Tracker, https://github.com/UoW-CPC/DocKubeADT/issues
Classifier: License :: OSI Approved :: Apache Software License
Classifier: Programming Language :: Python
Classifier: Programming Language :: Python :: 3
Classifier: Programming Language :: Python :: 3.8
Classifier: Programming Language :: Python :: Implementation :: CPython
Requires-Python: >=3.6
License-File: LICENSE
Requires-Dist: ruamel.yaml ~=0.18.2
Requires-Dist: click ~=8.1
